README.txt
setup.py
docs/HISTORY.txt
docs/INSTALL.txt
docs/LICENSE.GPL
docs/LICENSE.txt
qi/__init__.py
qi.jwMedia.egg-info/PKG-INFO
qi.jwMedia.egg-info/SOURCES.txt
qi.jwMedia.egg-info/dependency_links.txt
qi.jwMedia.egg-info/entry_points.txt
qi.jwMedia.egg-info/namespace_packages.txt
qi.jwMedia.egg-info/not-zip-safe
qi.jwMedia.egg-info/paster_plugins.txt
qi.jwMedia.egg-info/requires.txt
qi.jwMedia.egg-info/top_level.txt
qi/jwMedia/JWMediaSettings.py
qi/jwMedia/__init__.py
qi/jwMedia/config.py
qi/jwMedia/configure.zcml
qi/jwMedia/interfaces.py
qi/jwMedia/version.txt
qi/jwMedia/blobadapters/__init__.py
qi/jwMedia/blobadapters/configure.zcml
qi/jwMedia/blobadapters/schemaextenders.py
qi/jwMedia/browser/__init__.py
qi/jwMedia/browser/configure.zcml
qi/jwMedia/browser/flashvideo.pt
qi/jwMedia/browser/flashvideo.py
qi/jwMedia/browser/jwMediaSettings.py
qi/jwMedia/browser/mp3audio.pt
qi/jwMedia/browser/mp3audio.py
qi/jwMedia/browser/resources/audio.png
qi/jwMedia/browser/resources/flashvideo.kss
qi/jwMedia/browser/resources/mp3audio.kss
qi/jwMedia/browser/resources/player.swf
qi/jwMedia/browser/resources/swfobject.js
qi/jwMedia/browser/resources/video.png
qi/jwMedia/browser/resources/video45.png
qi/jwMedia/content/__init__.py
qi/jwMedia/content/audio.py
qi/jwMedia/content/configure.zcml
qi/jwMedia/content/video.py
qi/jwMedia/kss/__init__.py
qi/jwMedia/kss/commands.py
qi/jwMedia/kss/configure.zcml
qi/jwMedia/kss/interfaces.py
qi/jwMedia/kss/javascript/plugin.js
qi/jwMedia/locales/qi.jwMedia.pot
qi/jwMedia/locales/el/LC_MESSAGES/qi.jwMedia.mo
qi/jwMedia/locales/el/LC_MESSAGES/qi.jwMedia.po
qi/jwMedia/locales/en/LC_MESSAGES/qi.jwMedia.mo
qi/jwMedia/locales/en/LC_MESSAGES/qi.jwMedia.po
qi/jwMedia/portlets/__init__.py
qi/jwMedia/portlets/configure.zcml
qi/jwMedia/profiles/default/actionicons.xml
qi/jwMedia/profiles/default/componentregistry.xml
qi/jwMedia/profiles/default/controlpanel.xml
qi/jwMedia/profiles/default/factorytool.xml
qi/jwMedia/profiles/default/jsregistry.xml
qi/jwMedia/profiles/default/kssregistry.xml
qi/jwMedia/profiles/default/metadata.xml
qi/jwMedia/profiles/default/portlets.xml
qi/jwMedia/profiles/default/rolemap.xml
qi/jwMedia/profiles/default/types.xml
qi/jwMedia/profiles/default/types/Flash_Video.xml
qi/jwMedia/profiles/default/types/Mp3_Audio.xml
