Metadata-Version: 1.0
Name: qi.jwMedia
Version: 0.5b
Summary: A plone add-on for video/audio support using the JWPlayer
Home-page: http://qiweb.net
Author: G. Gozadinos
Author-email: ggozad@qiweb.net
License: GPL
Platform: UNKNOWN
Classifier: Framework :: Plone
Classifier: Programming Language :: Python
Classifier: Topic :: Software Development :: Libraries :: Python Modules
